{
    "1": {
        "timer_stats": {
            "timer_count": "9392351",
            "jitter_mean_usec": "3724.5248906077154",
            "jitter_min_usec": "-930.893",
            "jitter_max_usec": "34981417981.563",
            "jitter_std_usec": "11414325.489660338",
            "msg_count": "9392351",
            "deadline_misses_count": "0",
            "max_resident_set_size": "44536",
            "total_minor_pagefaults": "3028",
            "total_major_pagefaults": "0",
            "minor_pagefaults_active_node": "114",
            "major_pagefaults_active_node": "0",
            "voluntary_context_switches": "36992657",
            "involuntary_context_switches": "80203"
        },
        "sensor_stats": {
            "timer_count": "9392351",
            "jitter_mean_usec": "3724.5248906077154",
            "jitter_min_usec": "-930.893",
            "jitter_max_usec": "34981417981.563",
            "jitter_std_usec": "11414325.489660338",
            "msg_count": "9392351",
            "deadline_misses_count": "0",
            "max_resident_set_size": "44536",
            "total_minor_pagefaults": "3028",
            "total_major_pagefaults": "0",
            "minor_pagefaults_active_node": "114",
            "major_pagefaults_active_node": "0",
            "voluntary_context_switches": "36992657",
            "involuntary_context_switches": "80203"
        },
        "command_stats": {
            "timer_count": "9392351",
            "jitter_mean_usec": "3724.5248906077154",
            "jitter_min_usec": "-930.893",
            "jitter_max_usec": "34981417981.563",
            "jitter_std_usec": "11414325.489660338",
            "msg_count": "9392351",
            "deadline_misses_count": "0",
            "max_resident_set_size": "44536",
            "total_minor_pagefaults": "3028",
            "total_major_pagefaults": "0",
            "minor_pagefaults_active_node": "114",
            "major_pagefaults_active_node": "0",
            "voluntary_context_switches": "36992657",
            "involuntary_context_switches": "80203"
        },
        "rusage_stats": {
            "timer_count": "9392351",
            "jitter_mean_usec": "3724.5248906077154",
            "jitter_min_usec": "-930.893",
            "jitter_max_usec": "34981417981.563",
            "jitter_std_usec": "11414325.489660338",
            "msg_count": "9392351",
            "deadline_misses_count": "0",
            "max_resident_set_size": "44536",
            "total_minor_pagefaults": "3028",
            "total_major_pagefaults": "0",
            "minor_pagefaults_active_node": "114",
            "major_pagefaults_active_node": "0",
            "voluntary_context_switches": "36992657",
            "involuntary_context_switches": "80203"
        }
    },
    "3": {
        "timer_stats": {
            "timer_count": "9392451",
            "jitter_mean_usec": "3724.485236580273",
            "jitter_min_usec": "-930.893",
            "jitter_max_usec": "34981417981.563",
            "jitter_std_usec": "11414264.726203224",
            "msg_count": "9392451",
            "deadline_misses_count": "0",
            "max_resident_set_size": "44536",
            "total_minor_pagefaults": "3028",
            "total_major_pagefaults": "0",
            "minor_pagefaults_active_node": "114",
            "major_pagefaults_active_node": "0",
            "voluntary_context_switches": "36993050",
            "involuntary_context_switches": "80203"
        },
        "sensor_stats": {
            "timer_count": "9392451",
            "jitter_mean_usec": "3724.485236580273",
            "jitter_min_usec": "-930.893",
            "jitter_max_usec": "34981417981.563",
            "jitter_std_usec": "11414264.726203224",
            "msg_count": "9392451",
            "deadline_misses_count": "0",
            "max_resident_set_size": "44536",
            "total_minor_pagefaults": "3028",
            "total_major_pagefaults": "0",
            "minor_pagefaults_active_node": "114",
            "major_pagefaults_active_node": "0",
            "voluntary_context_switches": "36993050",
            "involuntary_context_switches": "80203"
        },
        "command_stats": {
            "timer_count": "9392451",
            "jitter_mean_usec": "3724.485236580273",
            "jitter_min_usec": "-930.893",
            "jitter_max_usec": "34981417981.563",
            "jitter_std_usec": "11414264.726203224",
            "msg_count": "9392451",
            "deadline_misses_count": "0",
            "max_resident_set_size": "44536",
            "total_minor_pagefaults": "3028",
            "total_major_pagefaults": "0",
            "minor_pagefaults_active_node": "114",
            "major_pagefaults_active_node": "0",
            "voluntary_context_switches": "36993050",
            "involuntary_context_switches": "80203"
        },
        "rusage_stats": {
            "timer_count": "9392451",
            "jitter_mean_usec": "3724.485236580273",
            "jitter_min_usec": "-930.893",
            "jitter_max_usec": "34981417981.563",
            "jitter_std_usec": "11414264.726203224",
            "msg_count": "9392451",
            "deadline_misses_count": "0",
            "max_resident_set_size": "44536",
            "total_minor_pagefaults": "3028",
            "total_major_pagefaults": "0",
            "minor_pagefaults_active_node": "114",
            "major_pagefaults_active_node": "0",
            "voluntary_context_switches": "36993050",
            "involuntary_context_switches": "80203"
        }
    },
    "5": {
        "timer_stats": {
            "timer_count": "9392551",
            "jitter_mean_usec": "3724.4455789219533",
            "jitter_min_usec": "-930.893",
            "jitter_max_usec": "34981417981.563",
            "jitter_std_usec": "11414203.96371651",
            "msg_count": "9392551",
            "deadline_misses_count": "0",
            "max_resident_set_size": "44536",
            "total_minor_pagefaults": "3028",
            "total_major_pagefaults": "0",
            "minor_pagefaults_active_node": "114",
            "major_pagefaults_active_node": "0",
            "voluntary_context_switches": "36993444",
            "involuntary_context_switches": "80205"
        },
        "sensor_stats": {
            "timer_count": "9392551",
            "jitter_mean_usec": "3724.4455789219533",
            "jitter_min_usec": "-930.893",
            "jitter_max_usec": "34981417981.563",
            "jitter_std_usec": "11414203.96371651",
            "msg_count": "9392551",
            "deadline_misses_count": "0",
            "max_resident_set_size": "44536",
            "total_minor_pagefaults": "3028",
            "total_major_pagefaults": "0",
            "minor_pagefaults_active_node": "114",
            "major_pagefaults_active_node": "0",
            "voluntary_context_switches": "36993444",
            "involuntary_context_switches": "80205"
        },
        "command_stats": {
            "timer_count": "9392551",
            "jitter_mean_usec": "3724.4455789219533",
            "jitter_min_usec": "-930.893",
            "jitter_max_usec": "34981417981.563",
            "jitter_std_usec": "11414203.96371651",
            "msg_count": "9392551",
            "deadline_misses_count": "0",
            "max_resident_set_size": "44536",
            "total_minor_pagefaults": "3028",
            "total_major_pagefaults": "0",
            "minor_pagefaults_active_node": "114",
            "major_pagefaults_active_node": "0",
            "voluntary_context_switches": "36993444",
            "involuntary_context_switches": "80205"
        },
        "rusage_stats": {
            "timer_count": "9392551",
            "jitter_mean_usec": "3724.4455789219533",
            "jitter_min_usec": "-930.893",
            "jitter_max_usec": "34981417981.563",
            "jitter_std_usec": "11414203.96371651",
            "msg_count": "9392551",
            "deadline_misses_count": "0",
            "max_resident_set_size": "44536",
            "total_minor_pagefaults": "3028",
            "total_major_pagefaults": "0",
            "minor_pagefaults_active_node": "114",
            "major_pagefaults_active_node": "0",
            "voluntary_context_switches": "36993444",
            "involuntary_context_switches": "80205"
        }
    },
    "7": {
        "timer_stats": {
            "timer_count": "9392651",
            "jitter_mean_usec": "3724.4059138719504",
            "jitter_min_usec": "-930.893",
            "jitter_max_usec": "34981417981.563",
            "jitter_std_usec": "11414143.202200174",
            "msg_count": "9392651",
            "deadline_misses_count": "0",
            "max_resident_set_size": "44536",
            "total_minor_pagefaults": "3028",
            "total_major_pagefaults": "0",
            "minor_pagefaults_active_node": "114",
            "major_pagefaults_active_node": "0",
            "voluntary_context_switches": "36993835",
            "involuntary_context_switches": "80206"
        },
        "sensor_stats": {
            "timer_count": "9392651",
            "jitter_mean_usec": "3724.4059138719504",
            "jitter_min_usec": "-930.893",
            "jitter_max_usec": "34981417981.563",
            "jitter_std_usec": "11414143.202200174",
            "msg_count": "9392651",
            "deadline_misses_count": "0",
            "max_resident_set_size": "44536",
            "total_minor_pagefaults": "3028",
            "total_major_pagefaults": "0",
            "minor_pagefaults_active_node": "114",
            "major_pagefaults_active_node": "0",
            "voluntary_context_switches": "36993835",
            "involuntary_context_switches": "80206"
        },
        "command_stats": {
            "timer_count": "9392651",
            "jitter_mean_usec": "3724.4059138719504",
            "jitter_min_usec": "-930.893",
            "jitter_max_usec": "34981417981.563",
            "jitter_std_usec": "11414143.202200174",
            "msg_count": "9392651",
            "deadline_misses_count": "0",
            "max_resident_set_size": "44536",
            "total_minor_pagefaults": "3028",
            "total_major_pagefaults": "0",
            "minor_pagefaults_active_node": "114",
            "major_pagefaults_active_node": "0",
            "voluntary_context_switches": "36993835",
            "involuntary_context_switches": "80206"
        },
        "rusage_stats": {
            "timer_count": "9392651",
            "jitter_mean_usec": "3724.4059138719504",
            "jitter_min_usec": "-930.893",
            "jitter_max_usec": "34981417981.563",
            "jitter_std_usec": "11414143.202200174",
            "msg_count": "9392651",
            "deadline_misses_count": "0",
            "max_resident_set_size": "44536",
            "total_minor_pagefaults": "3028",
            "total_major_pagefaults": "0",
            "minor_pagefaults_active_node": "114",
            "major_pagefaults_active_node": "0",
            "voluntary_context_switches": "36993835",
            "involuntary_context_switches": "80206"
        }
    },
    "9": {
        "timer_stats": {
            "timer_count": "9392751",
            "jitter_mean_usec": "3724.3662612821986",
            "jitter_min_usec": "-930.893",
            "jitter_max_usec": "34981417981.563",
            "jitter_std_usec": "11414082.441654185",
            "msg_count": "9392751",
            "deadline_misses_count": "0",
            "max_resident_set_size": "44536",
            "total_minor_pagefaults": "3028",
            "total_major_pagefaults": "0",
            "minor_pagefaults_active_node": "114",
            "major_pagefaults_active_node": "0",
            "voluntary_context_switches": "36994315",
            "involuntary_context_switches": "80206"
        },
        "sensor_stats": {
            "timer_count": "9392751",
            "jitter_mean_usec": "3724.3662612821986",
            "jitter_min_usec": "-930.893",
            "jitter_max_usec": "34981417981.563",
            "jitter_std_usec": "11414082.441654185",
            "msg_count": "9392751",
            "deadline_misses_count": "0",
            "max_resident_set_size": "44536",
            "total_minor_pagefaults": "3028",
            "total_major_pagefaults": "0",
            "minor_pagefaults_active_node": "114",
            "major_pagefaults_active_node": "0",
            "voluntary_context_switches": "36994315",
            "involuntary_context_switches": "80206"
        },
        "command_stats": {
            "timer_count": "9392751",
            "jitter_mean_usec": "3724.3662612821986",
            "jitter_min_usec": "-930.893",
            "jitter_max_usec": "34981417981.563",
            "jitter_std_usec": "11414082.441654185",
            "msg_count": "9392751",
            "deadline_misses_count": "0",
            "max_resident_set_size": "44536",
            "total_minor_pagefaults": "3028",
            "total_major_pagefaults": "0",
            "minor_pagefaults_active_node": "114",
            "major_pagefaults_active_node": "0",
            "voluntary_context_switches": "36994315",
            "involuntary_context_switches": "80206"
        },
        "rusage_stats": {
            "timer_count": "9392751",
            "jitter_mean_usec": "3724.3662612821986",
            "jitter_min_usec": "-930.893",
            "jitter_max_usec": "34981417981.563",
            "jitter_std_usec": "11414082.441654185",
            "msg_count": "9392751",
            "deadline_misses_count": "0",
            "max_resident_set_size": "44536",
            "total_minor_pagefaults": "3028",
            "total_major_pagefaults": "0",
            "minor_pagefaults_active_node": "114",
            "major_pagefaults_active_node": "0",
            "voluntary_context_switches": "36994315",
            "involuntary_context_switches": "80206"
        }
    },
    "11": {
        "timer_stats": {
            "timer_count": "9392851",
            "jitter_mean_usec": "3724.3266112299652",
            "jitter_min_usec": "-930.893",
            "jitter_max_usec": "34981417981.563",
            "jitter_std_usec": "11414021.682078524",
            "msg_count": "9392851",
            "deadline_misses_count": "0",
            "max_resident_set_size": "44536",
            "total_minor_pagefaults": "3028",
            "total_major_pagefaults": "0",
            "minor_pagefaults_active_node": "114",
            "major_pagefaults_active_node": "0",
            "voluntary_context_switches": "36994707",
            "involuntary_context_switches": "80207"
        },
        "sensor_stats": {
            "timer_count": "9392851",
            "jitter_mean_usec": "3724.3266112299652",
            "jitter_min_usec": "-930.893",
            "jitter_max_usec": "34981417981.563",
            "jitter_std_usec": "11414021.682078524",
            "msg_count": "9392851",
            "deadline_misses_count": "0",
            "max_resident_set_size": "44536",
            "total_minor_pagefaults": "3028",
            "total_major_pagefaults": "0",
            "minor_pagefaults_active_node": "114",
            "major_pagefaults_active_node": "0",
            "voluntary_context_switches": "36994707",
            "involuntary_context_switches": "80207"
        },
        "command_stats": {
            "timer_count": "9392851",
            "jitter_mean_usec": "3724.3266112299652",
            "jitter_min_usec": "-930.893",
            "jitter_max_usec": "34981417981.563",
            "jitter_std_usec": "11414021.682078524",
            "msg_count": "9392851",
            "deadline_misses_count": "0",
            "max_resident_set_size": "44536",
            "total_minor_pagefaults": "3028",
            "total_major_pagefaults": "0",
            "minor_pagefaults_active_node": "114",
            "major_pagefaults_active_node": "0",
            "voluntary_context_switches": "36994707",
            "involuntary_context_switches": "80207"
        },
        "rusage_stats": {
            "timer_count": "9392851",
            "jitter_mean_usec": "3724.3266112299652",
            "jitter_min_usec": "-930.893",
            "jitter_max_usec": "34981417981.563",
            "jitter_std_usec": "11414021.682078524",
            "msg_count": "9392851",
            "deadline_misses_count": "0",
            "max_resident_set_size": "44536",
            "total_minor_pagefaults": "3028",
            "total_major_pagefaults": "0",
            "minor_pagefaults_active_node": "114",
            "major_pagefaults_active_node": "0",
            "voluntary_context_switches": "36994707",
            "involuntary_context_switches": "80207"
        }
    },
    "13": {
        "timer_stats": {
            "timer_count": "9392951",
            "jitter_mean_usec": "3724.2869527074436",
            "jitter_min_usec": "-930.893",
            "jitter_max_usec": "34981417981.563",
            "jitter_std_usec": "11413960.923473157",
            "msg_count": "9392951",
            "deadline_misses_count": "0",
            "max_resident_set_size": "44536",
            "total_minor_pagefaults": "3028",
            "total_major_pagefaults": "0",
            "minor_pagefaults_active_node": "114",
            "major_pagefaults_active_node": "0",
            "voluntary_context_switches": "36995090",
            "involuntary_context_switches": "80207"
        },
        "sensor_stats": {
            "timer_count": "9392951",
            "jitter_mean_usec": "3724.2869527074436",
            "jitter_min_usec": "-930.893",
            "jitter_max_usec": "34981417981.563",
            "jitter_std_usec": "11413960.923473157",
            "msg_count": "9392951",
            "deadline_misses_count": "0",
            "max_resident_set_size": "44536",
            "total_minor_pagefaults": "3028",
            "total_major_pagefaults": "0",
            "minor_pagefaults_active_node": "114",
            "major_pagefaults_active_node": "0",
            "voluntary_context_switches": "36995090",
            "involuntary_context_switches": "80207"
        },
        "command_stats": {
            "timer_count": "9392951",
            "jitter_mean_usec": "3724.2869527074436",
            "jitter_min_usec": "-930.893",
            "jitter_max_usec": "34981417981.563",
            "jitter_std_usec": "11413960.923473157",
            "msg_count": "9392951",
            "deadline_misses_count": "0",
            "max_resident_set_size": "44536",
            "total_minor_pagefaults": "3028",
            "total_major_pagefaults": "0",
            "minor_pagefaults_active_node": "114",
            "major_pagefaults_active_node": "0",
            "voluntary_context_switches": "36995090",
            "involuntary_context_switches": "80207"
        },
        "rusage_stats": {
            "timer_count": "9392951",
            "jitter_mean_usec": "3724.2869527074436",
            "jitter_min_usec": "-930.893",
            "jitter_max_usec": "34981417981.563",
            "jitter_std_usec": "11413960.923473157",
            "msg_count": "9392951",
            "deadline_misses_count": "0",
            "max_resident_set_size": "44536",
            "total_minor_pagefaults": "3028",
            "total_major_pagefaults": "0",
            "minor_pagefaults_active_node": "114",
            "major_pagefaults_active_node": "0",
            "voluntary_context_switches": "36995090",
            "involuntary_context_switches": "80207"
        }
    },
    "15": {
        "timer_stats": {
            "timer_count": "9393051",
            "jitter_mean_usec": "3724.247297258759",
            "jitter_min_usec": "-930.893",
            "jitter_max_usec": "34981417981.563",
            "jitter_std_usec": "11413900.165838063",
            "msg_count": "9393051",
            "deadline_misses_count": "0",
            "max_resident_set_size": "44536",
            "total_minor_pagefaults": "3028",
            "total_major_pagefaults": "0",
            "minor_pagefaults_active_node": "114",
            "major_pagefaults_active_node": "0",
            "voluntary_context_switches": "36995475",
            "involuntary_context_switches": "80207"
        },
        "sensor_stats": {
            "timer_count": "9393051",
            "jitter_mean_usec": "3724.247297258759",
            "jitter_min_usec": "-930.893",
            "jitter_max_usec": "34981417981.563",
            "jitter_std_usec": "11413900.165838063",
            "msg_count": "9393051",
            "deadline_misses_count": "0",
            "max_resident_set_size": "44536",
            "total_minor_pagefaults": "3028",
            "total_major_pagefaults": "0",
            "minor_pagefaults_active_node": "114",
            "major_pagefaults_active_node": "0",
            "voluntary_context_switches": "36995475",
            "involuntary_context_switches": "80207"
        },
        "command_stats": {
            "timer_count": "9393051",
            "jitter_mean_usec": "3724.247297258759",
            "jitter_min_usec": "-930.893",
            "jitter_max_usec": "34981417981.563",
            "jitter_std_usec": "11413900.165838063",
            "msg_count": "9393051",
            "deadline_misses_count": "0",
            "max_resident_set_size": "44536",
            "total_minor_pagefaults": "3028",
            "total_major_pagefaults": "0",
            "minor_pagefaults_active_node": "114",
            "major_pagefaults_active_node": "0",
            "voluntary_context_switches": "36995475",
            "involuntary_context_switches": "80207"
        },
        "rusage_stats": {
            "timer_count": "9393051",
            "jitter_mean_usec": "3724.247297258759",
            "jitter_min_usec": "-930.893",
            "jitter_max_usec": "34981417981.563",
            "jitter_std_usec": "11413900.165838063",
            "msg_count": "9393051",
            "deadline_misses_count": "0",
            "max_resident_set_size": "44536",
            "total_minor_pagefaults": "3028",
            "total_major_pagefaults": "0",
            "minor_pagefaults_active_node": "114",
            "major_pagefaults_active_node": "0",
            "voluntary_context_switches": "36995475",
            "involuntary_context_switches": "80207"
        }
    },
    "17": {
        "timer_stats": {
            "timer_count": "9393151",
            "jitter_mean_usec": "3724.207644861882",
            "jitter_min_usec": "-930.893",
            "jitter_max_usec": "34981417981.563",
            "jitter_std_usec": "11413839.409173215",
            "msg_count": "9393151",
            "deadline_misses_count": "0",
            "max_resident_set_size": "44536",
            "total_minor_pagefaults": "3028",
            "total_major_pagefaults": "0",
            "minor_pagefaults_active_node": "114",
            "major_pagefaults_active_node": "0",
            "voluntary_context_switches": "36995861",
            "involuntary_context_switches": "80207"
        },
        "sensor_stats": {
            "timer_count": "9393151",
            "jitter_mean_usec": "3724.207644861882",
            "jitter_min_usec": "-930.893",
            "jitter_max_usec": "34981417981.563",
            "jitter_std_usec": "11413839.409173215",
            "msg_count": "9393151",
            "deadline_misses_count": "0",
            "max_resident_set_size": "44536",
            "total_minor_pagefaults": "3028",
            "total_major_pagefaults": "0",
            "minor_pagefaults_active_node": "114",
            "major_pagefaults_active_node": "0",
            "voluntary_context_switches": "36995861",
            "involuntary_context_switches": "80207"
        },
        "command_stats": {
            "timer_count": "9393151",
            "jitter_mean_usec": "3724.207644861882",
            "jitter_min_usec": "-930.893",
            "jitter_max_usec": "34981417981.563",
            "jitter_std_usec": "11413839.409173215",
            "msg_count": "9393151",
            "deadline_misses_count": "0",
            "max_resident_set_size": "44536",
            "total_minor_pagefaults": "3028",
            "total_major_pagefaults": "0",
            "minor_pagefaults_active_node": "114",
            "major_pagefaults_active_node": "0",
            "voluntary_context_switches": "36995861",
            "involuntary_context_switches": "80207"
        },
        "rusage_stats": {
            "timer_count": "9393151",
            "jitter_mean_usec": "3724.207644861882",
            "jitter_min_usec": "-930.893",
            "jitter_max_usec": "34981417981.563",
            "jitter_std_usec": "11413839.409173215",
            "msg_count": "9393151",
            "deadline_misses_count": "0",
            "max_resident_set_size": "44536",
            "total_minor_pagefaults": "3028",
            "total_major_pagefaults": "0",
            "minor_pagefaults_active_node": "114",
            "major_pagefaults_active_node": "0",
            "voluntary_context_switches": "36995861",
            "involuntary_context_switches": "80207"
        }
    },
    "19": {
        "timer_stats": {
            "timer_count": "9393251",
            "jitter_mean_usec": "3724.167989331742",
            "jitter_min_usec": "-930.893",
            "jitter_max_usec": "34981417981.563",
            "jitter_std_usec": "11413778.653478593",
            "msg_count": "9393251",
            "deadline_misses_count": "0",
            "max_resident_set_size": "44536",
            "total_minor_pagefaults": "3028",
            "total_major_pagefaults": "0",
            "minor_pagefaults_active_node": "114",
            "major_pagefaults_active_node": "0",
            "voluntary_context_switches": "36996296",
            "involuntary_context_switches": "80210"
        },
        "sensor_stats": {
            "timer_count": "9393251",
            "jitter_mean_usec": "3724.167989331742",
            "jitter_min_usec": "-930.893",
            "jitter_max_usec": "34981417981.563",
            "jitter_std_usec": "11413778.653478593",
            "msg_count": "9393251",
            "deadline_misses_count": "0",
            "max_resident_set_size": "44536",
            "total_minor_pagefaults": "3028",
            "total_major_pagefaults": "0",
            "minor_pagefaults_active_node": "114",
            "major_pagefaults_active_node": "0",
            "voluntary_context_switches": "36996296",
            "involuntary_context_switches": "80210"
        },
        "command_stats": {
            "timer_count": "9393251",
            "jitter_mean_usec": "3724.167989331742",
            "jitter_min_usec": "-930.893",
            "jitter_max_usec": "34981417981.563",
            "jitter_std_usec": "11413778.653478593",
            "msg_count": "9393251",
            "deadline_misses_count": "0",
            "max_resident_set_size": "44536",
            "total_minor_pagefaults": "3028",
            "total_major_pagefaults": "0",
            "minor_pagefaults_active_node": "114",
            "major_pagefaults_active_node": "0",
            "voluntary_context_switches": "36996296",
            "involuntary_context_switches": "80210"
        },
        "rusage_stats": {
            "timer_count": "9393251",
            "jitter_mean_usec": "3724.167989331742",
            "jitter_min_usec": "-930.893",
            "jitter_max_usec": "34981417981.563",
            "jitter_std_usec": "11413778.653478593",
            "msg_count": "9393251",
            "deadline_misses_count": "0",
            "max_resident_set_size": "44536",
            "total_minor_pagefaults": "3028",
            "total_major_pagefaults": "0",
            "minor_pagefaults_active_node": "114",
            "major_pagefaults_active_node": "0",
            "voluntary_context_switches": "36996296",
            "involuntary_context_switches": "80210"
        }
    },
    "21": {
        "timer_stats": {
            "timer_count": "9393351",
            "jitter_mean_usec": "3724.1283374181085",
            "jitter_min_usec": "-930.893",
            "jitter_max_usec": "34981417981.563",
            "jitter_std_usec": "11413717.898754165",
            "msg_count": "9393351",
            "deadline_misses_count": "0",
            "max_resident_set_size": "44536",
            "total_minor_pagefaults": "3028",
            "total_major_pagefaults": "0",
            "minor_pagefaults_active_node": "114",
            "major_pagefaults_active_node": "0",
            "voluntary_context_switches": "36996769",
            "involuntary_context_switches": "80210"
        },
        "sensor_stats": {
            "timer_count": "9393351",
            "jitter_mean_usec": "3724.1283374181085",
            "jitter_min_usec": "-930.893",
            "jitter_max_usec": "34981417981.563",
            "jitter_std_usec": "11413717.898754165",
            "msg_count": "9393351",
            "deadline_misses_count": "0",
            "max_resident_set_size": "44536",
            "total_minor_pagefaults": "3028",
            "total_major_pagefaults": "0",
            "minor_pagefaults_active_node": "114",
            "major_pagefaults_active_node": "0",
            "voluntary_context_switches": "36996769",
            "involuntary_context_switches": "80210"
        },
        "command_stats": {
            "timer_count": "9393351",
            "jitter_mean_usec": "3724.1283374181085",
            "jitter_min_usec": "-930.893",
            "jitter_max_usec": "34981417981.563",
            "jitter_std_usec": "11413717.898754165",
            "msg_count": "9393351",
            "deadline_misses_count": "0",
            "max_resident_set_size": "44536",
            "total_minor_pagefaults": "3028",
            "total_major_pagefaults": "0",
            "minor_pagefaults_active_node": "114",
            "major_pagefaults_active_node": "0",
            "voluntary_context_switches": "36996769",
            "involuntary_context_switches": "80210"
        },
        "rusage_stats": {
            "timer_count": "9393351",
            "jitter_mean_usec": "3724.1283374181085",
            "jitter_min_usec": "-930.893",
            "jitter_max_usec": "34981417981.563",
            "jitter_std_usec": "11413717.898754165",
            "msg_count": "9393351",
            "deadline_misses_count": "0",
            "max_resident_set_size": "44536",
            "total_minor_pagefaults": "3028",
            "total_major_pagefaults": "0",
            "minor_pagefaults_active_node": "114",
            "major_pagefaults_active_node": "0",
            "voluntary_context_switches": "36996769",
            "involuntary_context_switches": "80210"
        }
    },
    "23": {
        "timer_stats": {
            "timer_count": "9393451",
            "jitter_mean_usec": "3724.0886918509605",
            "jitter_min_usec": "-930.893",
            "jitter_max_usec": "34981417981.563",
            "jitter_std_usec": "11413657.144999906",
            "msg_count": "9393451",
            "deadline_misses_count": "0",
            "max_resident_set_size": "44536",
            "total_minor_pagefaults": "3028",
            "total_major_pagefaults": "0",
            "minor_pagefaults_active_node": "114",
            "major_pagefaults_active_node": "0",
            "voluntary_context_switches": "36997230",
            "involuntary_context_switches": "80214"
        },
        "sensor_stats": {
            "timer_count": "9393451",
            "jitter_mean_usec": "3724.0886918509605",
            "jitter_min_usec": "-930.893",
            "jitter_max_usec": "34981417981.563",
            "jitter_std_usec": "11413657.144999906",
            "msg_count": "9393451",
            "deadline_misses_count": "0",
            "max_resident_set_size": "44536",
            "total_minor_pagefaults": "3028",
            "total_major_pagefaults": "0",
            "minor_pagefaults_active_node": "114",
            "major_pagefaults_active_node": "0",
            "voluntary_context_switches": "36997230",
            "involuntary_context_switches": "80214"
        },
        "command_stats": {
            "timer_count": "9393451",
            "jitter_mean_usec": "3724.0886918509605",
            "jitter_min_usec": "-930.893",
            "jitter_max_usec": "34981417981.563",
            "jitter_std_usec": "11413657.144999906",
            "msg_count": "9393451",
            "deadline_misses_count": "0",
            "max_resident_set_size": "44536",
            "total_minor_pagefaults": "3028",
            "total_major_pagefaults": "0",
            "minor_pagefaults_active_node": "114",
            "major_pagefaults_active_node": "0",
            "voluntary_context_switches": "36997230",
            "involuntary_context_switches": "80214"
        },
        "rusage_stats": {
            "timer_count": "9393451",
            "jitter_mean_usec": "3724.0886918509605",
            "jitter_min_usec": "-930.893",
            "jitter_max_usec": "34981417981.563",
            "jitter_std_usec": "11413657.144999906",
            "msg_count": "9393451",
            "deadline_misses_count": "0",
            "max_resident_set_size": "44536",
            "total_minor_pagefaults": "3028",
            "total_major_pagefaults": "0",
            "minor_pagefaults_active_node": "114",
            "major_pagefaults_active_node": "0",
            "voluntary_context_switches": "36997230",
            "involuntary_context_switches": "80214"
        }
    },
    "25": {
        "timer_stats": {
            "timer_count": "9393551",
            "jitter_mean_usec": "3724.0490489660906",
            "jitter_min_usec": "-930.893",
            "jitter_max_usec": "34981417981.563",
            "jitter_std_usec": "11413596.392215785",
            "msg_count": "9393551",
            "deadline_misses_count": "0",
            "max_resident_set_size": "44536",
            "total_minor_pagefaults": "3028",
            "total_major_pagefaults": "0",
            "minor_pagefaults_active_node": "114",
            "major_pagefaults_active_node": "0",
            "voluntary_context_switches": "36997664",
            "involuntary_context_switches": "80215"
        },
        "sensor_stats": {
            "timer_count": "9393551",
            "jitter_mean_usec": "3724.0490489660906",
            "jitter_min_usec": "-930.893",
            "jitter_max_usec": "34981417981.563",
            "jitter_std_usec": "11413596.392215785",
            "msg_count": "9393551",
            "deadline_misses_count": "0",
            "max_resident_set_size": "44536",
            "total_minor_pagefaults": "3028",
            "total_major_pagefaults": "0",
            "minor_pagefaults_active_node": "114",
            "major_pagefaults_active_node": "0",
            "voluntary_context_switches": "36997664",
            "involuntary_context_switches": "80215"
        },
        "command_stats": {
            "timer_count": "9393551",
            "jitter_mean_usec": "3724.0490489660906",
            "jitter_min_usec": "-930.893",
            "jitter_max_usec": "34981417981.563",
            "jitter_std_usec": "11413596.392215785",
            "msg_count": "9393551",
            "deadline_misses_count": "0",
            "max_resident_set_size": "44536",
            "total_minor_pagefaults": "3028",
            "total_major_pagefaults": "0",
            "minor_pagefaults_active_node": "114",
            "major_pagefaults_active_node": "0",
            "voluntary_context_switches": "36997664",
            "involuntary_context_switches": "80215"
        },
        "rusage_stats": {
            "timer_count": "9393551",
            "jitter_mean_usec": "3724.0490489660906",
            "jitter_min_usec": "-930.893",
            "jitter_max_usec": "34981417981.563",
            "jitter_std_usec": "11413596.392215785",
            "msg_count": "9393551",
            "deadline_misses_count": "0",
            "max_resident_set_size": "44536",
            "total_minor_pagefaults": "3028",
            "total_major_pagefaults": "0",
            "minor_pagefaults_active_node": "114",
            "major_pagefaults_active_node": "0",
            "voluntary_context_switches": "36997664",
            "involuntary_context_switches": "80215"
        }
    },
    "27": {
        "timer_stats": {
            "timer_count": "9393651",
            "jitter_mean_usec": "3724.0093948067515",
            "jitter_min_usec": "-930.893",
            "jitter_max_usec": "34981417981.563",
            "jitter_std_usec": "11413535.640401779",
            "msg_count": "9393651",
            "deadline_misses_count": "0",
            "max_resident_set_size": "44536",
            "total_minor_pagefaults": "3028",
            "total_major_pagefaults": "0",
            "minor_pagefaults_active_node": "114",
            "major_pagefaults_active_node": "0",
            "voluntary_context_switches": "36998050",
            "involuntary_context_switches": "80219"
        },
        "sensor_stats": {
            "timer_count": "9393651",
            "jitter_mean_usec": "3724.0093948067515",
            "jitter_min_usec": "-930.893",
            "jitter_max_usec": "34981417981.563",
            "jitter_std_usec": "11413535.640401779",
            "msg_count": "9393651",
            "deadline_misses_count": "0",
            "max_resident_set_size": "44536",
            "total_minor_pagefaults": "3028",
            "total_major_pagefaults": "0",
            "minor_pagefaults_active_node": "114",
            "major_pagefaults_active_node": "0",
            "voluntary_context_switches": "36998050",
            "involuntary_context_switches": "80219"
        },
        "command_stats": {
            "timer_count": "9393651",
            "jitter_mean_usec": "3724.0093948067515",
            "jitter_min_usec": "-930.893",
            "jitter_max_usec": "34981417981.563",
            "jitter_std_usec": "11413535.640401779",
            "msg_count": "9393651",
            "deadline_misses_count": "0",
            "max_resident_set_size": "44536",
            "total_minor_pagefaults": "3028",
            "total_major_pagefaults": "0",
            "minor_pagefaults_active_node": "114",
            "major_pagefaults_active_node": "0",
            "voluntary_context_switches": "36998050",
            "involuntary_context_switches": "80219"
        },
        "rusage_stats": {
            "timer_count": "9393651",
            "jitter_mean_usec": "3724.0093948067515",
            "jitter_min_usec": "-930.893",
            "jitter_max_usec": "34981417981.563",
            "jitter_std_usec": "11413535.640401779",
            "msg_count": "9393651",
            "deadline_misses_count": "0",
            "max_resident_set_size": "44536",
            "total_minor_pagefaults": "3028",
            "total_major_pagefaults": "0",
            "minor_pagefaults_active_node": "114",
            "major_pagefaults_active_node": "0",
            "voluntary_context_switches": "36998050",
            "involuntary_context_switches": "80219"
        }
    },
    "29": {
        "timer_stats": {
            "timer_count": "9393751",
            "jitter_mean_usec": "3723.96974124843",
            "jitter_min_usec": "-930.893",
            "jitter_max_usec": "34981417981.563",
            "jitter_std_usec": "11413474.88955787",
            "msg_count": "9393751",
            "deadline_misses_count": "0",
            "max_resident_set_size": "44536",
            "total_minor_pagefaults": "3028",
            "total_major_pagefaults": "0",
            "minor_pagefaults_active_node": "114",
            "major_pagefaults_active_node": "0",
            "voluntary_context_switches": "36998461",
            "involuntary_context_switches": "80220"
        },
        "sensor_stats": {
            "timer_count": "9393751",
            "jitter_mean_usec": "3723.96974124843",
            "jitter_min_usec": "-930.893",
            "jitter_max_usec": "34981417981.563",
            "jitter_std_usec": "11413474.88955787",
            "msg_count": "9393751",
            "deadline_misses_count": "0",
            "max_resident_set_size": "44536",
            "total_minor_pagefaults": "3028",
            "total_major_pagefaults": "0",
            "minor_pagefaults_active_node": "114",
            "major_pagefaults_active_node": "0",
            "voluntary_context_switches": "36998461",
            "involuntary_context_switches": "80220"
        },
        "command_stats": {
            "timer_count": "9393751",
            "jitter_mean_usec": "3723.96974124843",
            "jitter_min_usec": "-930.893",
            "jitter_max_usec": "34981417981.563",
            "jitter_std_usec": "11413474.88955787",
            "msg_count": "9393751",
            "deadline_misses_count": "0",
            "max_resident_set_size": "44536",
            "total_minor_pagefaults": "3028",
            "total_major_pagefaults": "0",
            "minor_pagefaults_active_node": "114",
            "major_pagefaults_active_node": "0",
            "voluntary_context_switches": "36998461",
            "involuntary_context_switches": "80220"
        },
        "rusage_stats": {
            "timer_count": "9393751",
            "jitter_mean_usec": "3723.96974124843",
            "jitter_min_usec": "-930.893",
            "jitter_max_usec": "34981417981.563",
            "jitter_std_usec": "11413474.88955787",
            "msg_count": "9393751",
            "deadline_misses_count": "0",
            "max_resident_set_size": "44536",
            "total_minor_pagefaults": "3028",
            "total_major_pagefaults": "0",
            "minor_pagefaults_active_node": "114",
            "major_pagefaults_active_node": "0",
            "voluntary_context_switches": "36998461",
            "involuntary_context_switches": "80220"
        }
    },
    "31": {
        "timer_stats": {
            "timer_count": "9393851",
            "jitter_mean_usec": "3723.930095268122",
            "jitter_min_usec": "-930.893",
            "jitter_max_usec": "34981417981.563",
            "jitter_std_usec": "11413414.139684021",
            "msg_count": "9393851",
            "deadline_misses_count": "0",
            "max_resident_set_size": "44536",
            "total_minor_pagefaults": "3028",
            "total_major_pagefaults": "0",
            "minor_pagefaults_active_node": "114",
            "major_pagefaults_active_node": "0",
            "voluntary_context_switches": "36998902",
            "involuntary_context_switches": "80222"
        },
        "sensor_stats": {
            "timer_count": "9393851",
            "jitter_mean_usec": "3723.930095268122",
            "jitter_min_usec": "-930.893",
            "jitter_max_usec": "34981417981.563",
            "jitter_std_usec": "11413414.139684021",
            "msg_count": "9393851",
            "deadline_misses_count": "0",
            "max_resident_set_size": "44536",
            "total_minor_pagefaults": "3028",
            "total_major_pagefaults": "0",
            "minor_pagefaults_active_node": "114",
            "major_pagefaults_active_node": "0",
            "voluntary_context_switches": "36998902",
            "involuntary_context_switches": "80222"
        },
        "command_stats": {
            "timer_count": "9393851",
            "jitter_mean_usec": "3723.930095268122",
            "jitter_min_usec": "-930.893",
            "jitter_max_usec": "34981417981.563",
            "jitter_std_usec": "11413414.139684021",
            "msg_count": "9393851",
            "deadline_misses_count": "0",
            "max_resident_set_size": "44536",
            "total_minor_pagefaults": "3028",
            "total_major_pagefaults": "0",
            "minor_pagefaults_active_node": "114",
            "major_pagefaults_active_node": "0",
            "voluntary_context_switches": "36998902",
            "involuntary_context_switches": "80222"
        },
        "rusage_stats": {
            "timer_count": "9393851",
            "jitter_mean_usec": "3723.930095268122",
            "jitter_min_usec": "-930.893",
            "jitter_max_usec": "34981417981.563",
            "jitter_std_usec": "11413414.139684021",
            "msg_count": "9393851",
            "deadline_misses_count": "0",
            "max_resident_set_size": "44536",
            "total_minor_pagefaults": "3028",
            "total_major_pagefaults": "0",
            "minor_pagefaults_active_node": "114",
            "major_pagefaults_active_node": "0",
            "voluntary_context_switches": "36998902",
            "involuntary_context_switches": "80222"
        }
    },
    "33": {
        "timer_stats": {
            "timer_count": "9393951",
            "jitter_mean_usec": "3723.890459008133",
            "jitter_min_usec": "-930.893",
            "jitter_max_usec": "34981417981.563",
            "jitter_std_usec": "11413353.390780209",
            "msg_count": "9393951",
            "deadline_misses_count": "0",
            "max_resident_set_size": "44536",
            "total_minor_pagefaults": "3028",
            "total_major_pagefaults": "0",
            "minor_pagefaults_active_node": "114",
            "major_pagefaults_active_node": "0",
            "voluntary_context_switches": "36999313",
            "involuntary_context_switches": "80227"
        },
        "sensor_stats": {
            "timer_count": "9393951",
            "jitter_mean_usec": "3723.890459008133",
            "jitter_min_usec": "-930.893",
            "jitter_max_usec": "34981417981.563",
            "jitter_std_usec": "11413353.390780209",
            "msg_count": "9393951",
            "deadline_misses_count": "0",
            "max_resident_set_size": "44536",
            "total_minor_pagefaults": "3028",
            "total_major_pagefaults": "0",
            "minor_pagefaults_active_node": "114",
            "major_pagefaults_active_node": "0",
            "voluntary_context_switches": "36999313",
            "involuntary_context_switches": "80227"
        },
        "command_stats": {
            "timer_count": "9393951",
            "jitter_mean_usec": "3723.890459008133",
            "jitter_min_usec": "-930.893",
            "jitter_max_usec": "34981417981.563",
            "jitter_std_usec": "11413353.390780209",
            "msg_count": "9393951",
            "deadline_misses_count": "0",
            "max_resident_set_size": "44536",
            "total_minor_pagefaults": "3028",
            "total_major_pagefaults": "0",
            "minor_pagefaults_active_node": "114",
            "major_pagefaults_active_node": "0",
            "voluntary_context_switches": "36999313",
            "involuntary_context_switches": "80227"
        },
        "rusage_stats": {
            "timer_count": "9393951",
            "jitter_mean_usec": "3723.890459008133",
            "jitter_min_usec": "-930.893",
            "jitter_max_usec": "34981417981.563",
            "jitter_std_usec": "11413353.390780209",
            "msg_count": "9393951",
            "deadline_misses_count": "0",
            "max_resident_set_size": "44536",
            "total_minor_pagefaults": "3028",
            "total_major_pagefaults": "0",
            "minor_pagefaults_active_node": "114",
            "major_pagefaults_active_node": "0",
            "voluntary_context_switches": "36999313",
            "involuntary_context_switches": "80227"
        }
    },
    "35": {
        "timer_stats": {
            "timer_count": "9394051",
            "jitter_mean_usec": "3723.850807109228",
            "jitter_min_usec": "-930.893",
            "jitter_max_usec": "34981417981.563",
            "jitter_std_usec": "11413292.642846417",
            "msg_count": "9394051",
            "deadline_misses_count": "0",
            "max_resident_set_size": "44536",
            "total_minor_pagefaults": "3028",
            "total_major_pagefaults": "0",
            "minor_pagefaults_active_node": "114",
            "major_pagefaults_active_node": "0",
            "voluntary_context_switches": "36999697",
            "involuntary_context_switches": "80231"
        },
        "sensor_stats": {
            "timer_count": "9394051",
            "jitter_mean_usec": "3723.850807109228",
            "jitter_min_usec": "-930.893",
            "jitter_max_usec": "34981417981.563",
            "jitter_std_usec": "11413292.642846417",
            "msg_count": "9394051",
            "deadline_misses_count": "0",
            "max_resident_set_size": "44536",
            "total_minor_pagefaults": "3028",
            "total_major_pagefaults": "0",
            "minor_pagefaults_active_node": "114",
            "major_pagefaults_active_node": "0",
            "voluntary_context_switches": "36999697",
            "involuntary_context_switches": "80231"
        },
        "command_stats": {
            "timer_count": "9394051",
            "jitter_mean_usec": "3723.850807109228",
            "jitter_min_usec": "-930.893",
            "jitter_max_usec": "34981417981.563",
            "jitter_std_usec": "11413292.642846417",
            "msg_count": "9394051",
            "deadline_misses_count": "0",
            "max_resident_set_size": "44536",
            "total_minor_pagefaults": "3028",
            "total_major_pagefaults": "0",
            "minor_pagefaults_active_node": "114",
            "major_pagefaults_active_node": "0",
            "voluntary_context_switches": "36999697",
            "involuntary_context_switches": "80231"
        },
        "rusage_stats": {
            "timer_count": "9394051",
            "jitter_mean_usec": "3723.850807109228",
            "jitter_min_usec": "-930.893",
            "jitter_max_usec": "34981417981.563",
            "jitter_std_usec": "11413292.642846417",
            "msg_count": "9394051",
            "deadline_misses_count": "0",
            "max_resident_set_size": "44536",
            "total_minor_pagefaults": "3028",
            "total_major_pagefaults": "0",
            "minor_pagefaults_active_node": "114",
            "major_pagefaults_active_node": "0",
            "voluntary_context_switches": "36999697",
            "involuntary_context_switches": "80231"
        }
    },
    "37": {
        "timer_stats": {
            "timer_count": "9394151",
            "jitter_mean_usec": "3723.811159455454",
            "jitter_min_usec": "-930.893",
            "jitter_max_usec": "34981417981.563",
            "jitter_std_usec": "11413231.89588261",
            "msg_count": "9394151",
            "deadline_misses_count": "0",
            "max_resident_set_size": "44536",
            "total_minor_pagefaults": "3028",
            "total_major_pagefaults": "0",
            "minor_pagefaults_active_node": "114",
            "major_pagefaults_active_node": "0",
            "voluntary_context_switches": "37000104",
            "involuntary_context_switches": "80232"
        },
        "sensor_stats": {
            "timer_count": "9394151",
            "jitter_mean_usec": "3723.811159455454",
            "jitter_min_usec": "-930.893",
            "jitter_max_usec": "34981417981.563",
            "jitter_std_usec": "11413231.89588261",
            "msg_count": "9394151",
            "deadline_misses_count": "0",
            "max_resident_set_size": "44536",
            "total_minor_pagefaults": "3028",
            "total_major_pagefaults": "0",
            "minor_pagefaults_active_node": "114",
            "major_pagefaults_active_node": "0",
            "voluntary_context_switches": "37000104",
            "involuntary_context_switches": "80232"
        },
        "command_stats": {
            "timer_count": "9394151",
            "jitter_mean_usec": "3723.811159455454",
            "jitter_min_usec": "-930.893",
            "jitter_max_usec": "34981417981.563",
            "jitter_std_usec": "11413231.89588261",
            "msg_count": "9394151",
            "deadline_misses_count": "0",
            "max_resident_set_size": "44536",
            "total_minor_pagefaults": "3028",
            "total_major_pagefaults": "0",
            "minor_pagefaults_active_node": "114",
            "major_pagefaults_active_node": "0",
            "voluntary_context_switches": "37000104",
            "involuntary_context_switches": "80232"
        },
        "rusage_stats": {
            "timer_count": "9394151",
            "jitter_mean_usec": "3723.811159455454",
            "jitter_min_usec": "-930.893",
            "jitter_max_usec": "34981417981.563",
            "jitter_std_usec": "11413231.89588261",
            "msg_count": "9394151",
            "deadline_misses_count": "0",
            "max_resident_set_size": "44536",
            "total_minor_pagefaults": "3028",
            "total_major_pagefaults": "0",
            "minor_pagefaults_active_node": "114",
            "major_pagefaults_active_node": "0",
            "voluntary_context_switches": "37000104",
            "involuntary_context_switches": "80232"
        }
    },
    "39": {
        "timer_stats": {
            "timer_count": "9394251",
            "jitter_mean_usec": "3723.771525828825",
            "jitter_min_usec": "-930.893",
            "jitter_max_usec": "34981417981.563",
            "jitter_std_usec": "11413171.149888761",
            "msg_count": "9394251",
            "deadline_misses_count": "0",
            "max_resident_set_size": "44536",
            "total_minor_pagefaults": "3028",
            "total_major_pagefaults": "0",
            "minor_pagefaults_active_node": "114",
            "major_pagefaults_active_node": "0",
            "voluntary_context_switches": "37000516",
            "involuntary_context_switches": "80233"
        },
        "sensor_stats": {
            "timer_count": "9394251",
            "jitter_mean_usec": "3723.771525828825",
            "jitter_min_usec": "-930.893",
            "jitter_max_usec": "34981417981.563",
            "jitter_std_usec": "11413171.149888761",
            "msg_count": "9394251",
            "deadline_misses_count": "0",
            "max_resident_set_size": "44536",
            "total_minor_pagefaults": "3028",
            "total_major_pagefaults": "0",
            "minor_pagefaults_active_node": "114",
            "major_pagefaults_active_node": "0",
            "voluntary_context_switches": "37000516",
            "involuntary_context_switches": "80233"
        },
        "command_stats": {
            "timer_count": "9394251",
            "jitter_mean_usec": "3723.771525828825",
            "jitter_min_usec": "-930.893",
            "jitter_max_usec": "34981417981.563",
            "jitter_std_usec": "11413171.149888761",
            "msg_count": "9394251",
            "deadline_misses_count": "0",
            "max_resident_set_size": "44536",
            "total_minor_pagefaults": "3028",
            "total_major_pagefaults": "0",
            "minor_pagefaults_active_node": "114",
            "major_pagefaults_active_node": "0",
            "voluntary_context_switches": "37000516",
            "involuntary_context_switches": "80233"
        },
        "rusage_stats": {
            "timer_count": "9394251",
            "jitter_mean_usec": "3723.771525828825",
            "jitter_min_usec": "-930.893",
            "jitter_max_usec": "34981417981.563",
            "jitter_std_usec": "11413171.149888761",
            "msg_count": "9394251",
            "deadline_misses_count": "0",
            "max_resident_set_size": "44536",
            "total_minor_pagefaults": "3028",
            "total_major_pagefaults": "0",
            "minor_pagefaults_active_node": "114",
            "major_pagefaults_active_node": "0",
            "voluntary_context_switches": "37000516",
            "involuntary_context_switches": "80233"
        }
    },
    "41": {
        "timer_stats": {
            "timer_count": "9394351",
            "jitter_mean_usec": "3723.7318786252836",
            "jitter_min_usec": "-930.893",
            "jitter_max_usec": "34981417981.563",
            "jitter_std_usec": "11413110.404864863",
            "msg_count": "9394351",
            "deadline_misses_count": "0",
            "max_resident_set_size": "44536",
            "total_minor_pagefaults": "3028",
            "total_major_pagefaults": "0",
            "minor_pagefaults_active_node": "114",
            "major_pagefaults_active_node": "0",
            "voluntary_context_switches": "37000906",
            "involuntary_context_switches": "80234"
        },
        "sensor_stats": {
            "timer_count": "9394351",
            "jitter_mean_usec": "3723.7318786252836",
            "jitter_min_usec": "-930.893",
            "jitter_max_usec": "34981417981.563",
            "jitter_std_usec": "11413110.404864863",
            "msg_count": "9394351",
            "deadline_misses_count": "0",
            "max_resident_set_size": "44536",
            "total_minor_pagefaults": "3028",
            "total_major_pagefaults": "0",
            "minor_pagefaults_active_node": "114",
            "major_pagefaults_active_node": "0",
            "voluntary_context_switches": "37000906",
            "involuntary_context_switches": "80234"
        },
        "command_stats": {
            "timer_count": "9394351",
            "jitter_mean_usec": "3723.7318786252836",
            "jitter_min_usec": "-930.893",
            "jitter_max_usec": "34981417981.563",
            "jitter_std_usec": "11413110.404864863",
            "msg_count": "9394351",
            "deadline_misses_count": "0",
            "max_resident_set_size": "44536",
            "total_minor_pagefaults": "3028",
            "total_major_pagefaults": "0",
            "minor_pagefaults_active_node": "114",
            "major_pagefaults_active_node": "0",
            "voluntary_context_switches": "37000906",
            "involuntary_context_switches": "80234"
        },
        "rusage_stats": {
            "timer_count": "9394351",
            "jitter_mean_usec": "3723.7318786252836",
            "jitter_min_usec": "-930.893",
            "jitter_max_usec": "34981417981.563",
            "jitter_std_usec": "11413110.404864863",
            "msg_count": "9394351",
            "deadline_misses_count": "0",
            "max_resident_set_size": "44536",
            "total_minor_pagefaults": "3028",
            "total_major_pagefaults": "0",
            "minor_pagefaults_active_node": "114",
            "major_pagefaults_active_node": "0",
            "voluntary_context_switches": "37000906",
            "involuntary_context_switches": "80234"
        }
    },
    "43": {
        "timer_stats": {
            "timer_count": "9394451",
            "jitter_mean_usec": "3723.6922354236176",
            "jitter_min_usec": "-930.893",
            "jitter_max_usec": "34981417981.563",
            "jitter_std_usec": "11413049.660810871",
            "msg_count": "9394451",
            "deadline_misses_count": "0",
            "max_resident_set_size": "44536",
            "total_minor_pagefaults": "3028",
            "total_major_pagefaults": "0",
            "minor_pagefaults_active_node": "114",
            "major_pagefaults_active_node": "0",
            "voluntary_context_switches": "37001313",
            "involuntary_context_switches": "80234"
        },
        "sensor_stats": {
            "timer_count": "9394451",
            "jitter_mean_usec": "3723.6922354236176",
            "jitter_min_usec": "-930.893",
            "jitter_max_usec": "34981417981.563",
            "jitter_std_usec": "11413049.660810871",
            "msg_count": "9394451",
            "deadline_misses_count": "0",
            "max_resident_set_size": "44536",
            "total_minor_pagefaults": "3028",
            "total_major_pagefaults": "0",
            "minor_pagefaults_active_node": "114",
            "major_pagefaults_active_node": "0",
            "voluntary_context_switches": "37001313",
            "involuntary_context_switches": "80234"
        },
        "command_stats": {
            "timer_count": "9394451",
            "jitter_mean_usec": "3723.6922354236176",
            "jitter_min_usec": "-930.893",
            "jitter_max_usec": "34981417981.563",
            "jitter_std_usec": "11413049.660810871",
            "msg_count": "9394451",
            "deadline_misses_count": "0",
            "max_resident_set_size": "44536",
            "total_minor_pagefaults": "3028",
            "total_major_pagefaults": "0",
            "minor_pagefaults_active_node": "114",
            "major_pagefaults_active_node": "0",
            "voluntary_context_switches": "37001313",
            "involuntary_context_switches": "80234"
        },
        "rusage_stats": {
            "timer_count": "9394451",
            "jitter_mean_usec": "3723.6922354236176",
            "jitter_min_usec": "-930.893",
            "jitter_max_usec": "34981417981.563",
            "jitter_std_usec": "11413049.660810871",
            "msg_count": "9394451",
            "deadline_misses_count": "0",
            "max_resident_set_size": "44536",
            "total_minor_pagefaults": "3028",
            "total_major_pagefaults": "0",
            "minor_pagefaults_active_node": "114",
            "major_pagefaults_active_node": "0",
            "voluntary_context_switches": "37001313",
            "involuntary_context_switches": "80234"
        }
    }
}